{
  "global": {
    "BLACK  &  WHITE": {
      "Black": {
        "value": "#000000",
        "type": "color"
      },
      "White": {
        "value": "#ffffff",
        "type": "color"
      }
    },
    "GRAYSCALE": {
      "Gray 100": {
        "value": "#f2f2f2",
        "type": "color"
      },
      "Gray 200": {
        "value": "#e6e6e6",
        "type": "color"
      },
      "Gray 300": {
        "value": "#c8c8c8",
        "type": "color"
      },
      "Gray 400": {
        "value": "#a0a0a0",
        "type": "color"
      },
      "Gray 500": {
        "value": "#78787d",
        "type": "color"
      },
      "Gray 600": {
        "value": "#5a5a5f",
        "type": "color"
      },
      "Gray 700": {
        "value": "#3c3c41",
        "type": "color"
      },
      "Gray 800": {
        "value": "#1c1c1e",
        "type": "color"
      }
    },
    "COLORS": {
      "RED": {
        "Red 100": {
          "value": "#fecdd2",
          "type": "color"
        },
        "Red 200": {
          "value": "#ff8a80",
          "type": "color"
        },
        "Red 300": {
          "value": "#ff4545",
          "type": "color"
        },
        "Red 400": {
          "value": "#d70015",
          "type": "color"
        }
      },
      "ORANGE": {
        "Orange 100": {
          "value": "#ffe0b2",
          "type": "color"
        },
        "Orange 200": {
          "value": "#ffa400",
          "type": "color"
        },
        "Orange 300": {
          "value": "#f57c00",
          "type": "color"
        },
        "Orange 400": {
          "value": "#e65100",
          "type": "color"
        }
      },
      "GREEN": {
        "Green 100": {
          "value": "#e8f5e9",
          "type": "color"
        },
        "Green 200": {
          "value": "#01d234",
          "type": "color"
        },
        "Green 300": {
          "value": "#78be21",
          "type": "color"
        },
        "Green 400": {
          "value": "#097a11",
          "type": "color"
        }
      },
      "TEAL": {
        "Teal 100": {
          "value": "#d2ffeb",
          "type": "color"
        },
        "Teal 200": {
          "value": "#12e0b0",
          "type": "color"
        },
        "Teal 300": {
          "value": "#00956f",
          "type": "color"
        },
        "Teal 400": {
          "value": "#00695c",
          "type": "color"
        }
      },
      "CYAN": {
        "Cyan 100": {
          "value": "#b2ebf2",
          "type": "color"
        },
        "Cyan 200": {
          "value": "#00bcd4",
          "type": "color"
        },
        "Cyan 300": {
          "value": "#007c91",
          "type": "color"
        },
        "Cyan 400": {
          "value": "#006078",
          "type": "color"
        }
      },
      "BLUE": {
        "Blue 100": {
          "value": "#99d6ea",
          "type": "color"
        },
        "Blue 200": {
          "value": "#009fdb",
          "type": "color"
        },
        "Blue 300": {
          "value": "#0082e6",
          "type": "color"
        },
        "Blue 400": {
          "value": "#0067b9",
          "type": "color"
        }
      },
      "INDIGO": {
        "Indigo 100": {
          "value": "#a8b1eb",
          "type": "color"
        },
        "Indigo 200": {
          "value": "#6e79f5",
          "type": "color"
        },
        "Indigo 300": {
          "value": "#3f51b5",
          "type": "color"
        },
        "Indigo 400": {
          "value": "#003865",
          "type": "color"
        }
      },
      "PURPLE": {
        "Purple 100": {
          "value": "#e1bee7",
          "type": "color"
        },
        "Purple 200": {
          "value": "#bf5af2",
          "type": "color"
        },
        "Purple 300": {
          "value": "#753bbd",
          "type": "color"
        },
        "Purple 400": {
          "value": "#343579",
          "type": "color"
        }
      }
    },
    "STATES": {
      "BLACK": {
        "Resting": {
          "value": "#00000000",
          "type": "color"
        },
        "Hover": {
          "value": "#0000000a",
          "type": "color"
        },
        "Focus": {
          "value": "#0000001f",
          "type": "color"
        },
        "Pressed": {
          "value": "#0000001a",
          "type": "color"
        },
        "Dragged": {
          "value": "#00000014",
          "type": "color"
        },
        "Selected": {
          "value": "#00000014",
          "type": "color"
        },
        "Disabled": {
          "value": "#ffffff00",
          "type": "color"
        }
      },
      "WHITE": {
        "Resting": {
          "value": "#ffffff00",
          "type": "color"
        },
        "Hover": {
          "value": "#ffffff0a",
          "type": "color"
        },
        "Focus": {
          "value": "#ffffff1f",
          "type": "color"
        },
        "Pressed": {
          "value": "#ffffff1a",
          "type": "color"
        },
        "Dragged": {
          "value": "#ffffff14",
          "type": "color"
        },
        "Selected": {
          "value": "#ffffff14",
          "type": "color"
        },
        "Disabled": {
          "value": "#0000001f",
          "type": "color"
        }
      },
      "BLUE": {
        "Resting": {
          "value": "#0067b900",
          "type": "color"
        },
        "Hover": {
          "value": "#0067b914",
          "type": "color"
        },
        "Focus": {
          "value": "#0067b91f",
          "type": "color"
        },
        "Pressed": {
          "value": "#0067b91a",
          "type": "color"
        },
        "Dragged": {
          "value": "#0067b914",
          "type": "color"
        },
        "Selected": {
          "value": "#0067b914",
          "type": "color"
        },
        "Disabled": {
          "value": "#ffffff00",
          "type": "color"
        }
      },
      "RED": {
        "Resting": {
          "value": "#d7001500",
          "type": "color"
        },
        "Hover": {
          "value": "#d7001514",
          "type": "color"
        },
        "Focus": {
          "value": "#d700151f",
          "type": "color"
        },
        "Pressed": {
          "value": "#d700151a",
          "type": "color"
        },
        "Dragged": {
          "value": "#d7001514",
          "type": "color"
        },
        "Selected": {
          "value": "#d7001514",
          "type": "color"
        },
        "Disabled": {
          "value": "#ffffff00",
          "type": "color"
        }
      }
    }
  },
  "$themes": []
}